Metadata-Version: 2.1
Name: alg0sss
Version: 0.0
Summary: alg0sss
Author-email: applepro285@gmail.com
